os2mo_dar_client/__init__.py
os2mo_dar_client/cli.py
os2mo_dar_client/dar_client.py
os2mo_dar_client/py.typed
os2mo_dar_client-1.0.4.dist-info/LICENSE
os2mo_dar_client-1.0.4.dist-info/LICENSES/MPL-2.0.txt
os2mo_dar_client-1.0.4.dist-info/METADATA
os2mo_dar_client-1.0.4.dist-info/WHEEL
os2mo_dar_client-1.0.4.dist-info/RECORD
