Metadata-Version: 2.1
Name: os2mo-dar-client
Version: 1.0.4
Summary: OS2mo DAR Client is a client for DAWA / DAR
Home-page: https://magenta.dk/
License: MPL-2.0
Keywords: os2mo,lora,dar,client
Author: Magenta
Author-email: info@magenta.dk
Requires-Python: >=3.8,<4.0
Classifier: License :: OSI Approved
Classifier: Programming Language :: Python :: 3
Classifier: Programming Language :: Python :: 3.8
Classifier: Programming Language :: Python :: 3.9
Classifier: Programming Language :: Python :: 3.10
Classifier: Programming Language :: Python :: 3.11
Classifier: Programming Language :: Python :: 3.12
Requires-Dist: aiohttp (>=3.7.4,<4.0.0)
Requires-Dist: click (>=8.0.1,<9.0.0)
Requires-Dist: more-itertools (>=9.1.0,<10.0.0)
Requires-Dist: ra-utils (>=1,<2)
Requires-Dist: tenacity (>=8.0.1,<9.0.0)
Project-URL: Repository, https://git.magenta.dk/rammearkitektur/ra-utils
